AsyncioPySide6/__init__.py
AsyncioPySide6/nvd/AsyncioPySide6.py
AsyncioPySide6/nvd/__init__.py
AsyncioPySide6/tests/__init__.py
AsyncioPySide6/tests/test_AsyncioPySide6.py
nvd/AsyncioPySide6.py
nvd/__init__.py
tests/__init__.py
tests/test_AsyncioPySide6.py
AsyncioPySide6-0.3.2.dist-info/LICENSE
AsyncioPySide6-0.3.2.dist-info/METADATA
AsyncioPySide6-0.3.2.dist-info/WHEEL
AsyncioPySide6-0.3.2.dist-info/top_level.txt
AsyncioPySide6-0.3.2.dist-info/RECORD
