Metadata-Version: 2.1
Name: AsyncioPySide6
Version: 0.3.2
License-File: LICENSE
Requires-Dist: PySide6
